LICENSE.txt
MANIFEST.in
README.md
ez_setup.py
setup.cfg
setup.py
MLCLAS.egg-info/.DS_Store
MLCLAS.egg-info/PKG-INFO
MLCLAS.egg-info/SOURCES.txt
MLCLAS.egg-info/dependency_links.txt
MLCLAS.egg-info/requires.txt
MLCLAS.egg-info/top_level.txt
mlclas/.DS_Store
mlclas/__init__.py
mlclas/__pycache__/__init__.cpython-35.pyc
mlclas/ensemble/.DS_Store
mlclas/ensemble/__init__.py
mlclas/ensemble/ensembles.py
mlclas/ensemble/__pycache__/__init__.cpython-35.pyc
mlclas/ensemble/__pycache__/ensembles.cpython-35.pyc
mlclas/neural/__init__.py
mlclas/neural/bpmll.py
mlclas/neural/bpmll_models.py
mlclas/neural/__pycache__/__init__.cpython-35.pyc
mlclas/neural/__pycache__/bpmll.cpython-35.pyc
mlclas/neural/__pycache__/bpmll_models.cpython-35.pyc
mlclas/stats/Normalizer.py
mlclas/stats/__init__.py
mlclas/stats/metrics.py
mlclas/stats/__pycache__/Normalizer.cpython-35.pyc
mlclas/stats/__pycache__/__init__.cpython-35.pyc
mlclas/stats/__pycache__/metrics.cpython-35.pyc
mlclas/svm/__init__.py
mlclas/svm/ranking_svm.py
mlclas/svm/rankingsvm_models.py
mlclas/svm/__pycache__/__init__.cpython-35.pyc
mlclas/svm/__pycache__/ranking_svm.cpython-35.pyc
mlclas/svm/__pycache__/rankingsvm_models.cpython-35.pyc
mlclas/tree/__init__.py
mlclas/tree/dt_models.py
mlclas/tree/ml_dt.py
mlclas/tree/__pycache__/__init__.cpython-35.pyc
mlclas/tree/__pycache__/dt_models.cpython-35.pyc
mlclas/tree/__pycache__/ml_dt.cpython-35.pyc
mlclas/utils/__init__.py
mlclas/utils/check.py
mlclas/utils/persist_reuters.py
mlclas/utils/__pycache__/Stats.cpython-35.pyc
mlclas/utils/__pycache__/__init__.cpython-35.pyc
mlclas/utils/__pycache__/check.cpython-35.pyc